src/__init__.py
src/cbrext.py
src/cli.py
src/extract.py
src/save.py
src/util.py
cbrext-0.1.0.dist-info/LICENSE
cbrext-0.1.0.dist-info/METADATA
cbrext-0.1.0.dist-info/WHEEL
cbrext-0.1.0.dist-info/entry_points.txt
cbrext-0.1.0.dist-info/top_level.txt
cbrext-0.1.0.dist-info/RECORD
