Metadata-Version: 2.1
Name: cbrext
Version: 0.1.0
Summary: This tool extracts the Compressed Beamforming Report data from a PCAP file and saves it to a JSON file.
Home-page: https://github.com/kimbank/cbr-extractor
Author: kimbank
Author-email: kimbank@kimbank.dev
Classifier: Programming Language :: Python :: 3
Requires-Python: >=3.9
License-File: LICENSE
Requires-Dist: pandas~=2.2.2
